goapauto/__init__.py
goapauto/models/__init__.py
goapauto/models/action_provider.py
goapauto/models/actions.py
goapauto/models/goal.py
goapauto/models/goal_arbitrator.py
goapauto/models/goap_planner.py
goapauto/models/node.py
goapauto/models/sensors.py
goapauto/models/worldstate.py
goapauto/py.typed
goapauto/utils/visualizer.py
goapauto-0.2.1.dist-info/WHEEL
goapauto-0.2.1.dist-info/METADATA
goapauto-0.2.1.dist-info/RECORD
