Metadata-Version: 2.3
Name: goapauto
Version: 0.2.1
Summary: A flexible Goal-Oriented Action Planning (GOAP) system for game AI and planning problems, featuring A* search, efficient state management, and modular design.
Author: IAmNo1Special
Author-email: IAmNo1Special <ivmno1special@gmail.com>
Requires-Dist: pydantic>=2.12.5
Requires-Python: ==3.13.*
